lockbox_sdk/__init__.py
lockbox_sdk/client.py
lockbox_sdk/dto.py
lockbox_sdk/error.py
lockbox_sdk/py.typed
lockbox_sdk/sdk.py
lockbox_sdk/utils.py
lockbox_sdk/v1/__init__.py
lockbox_sdk/v1/client.py
lockbox_sdk/v1/api_keys/__init__.py
lockbox_sdk/v1/api_keys/api.py
lockbox_sdk/v1/api_keys/client.py
lockbox_sdk/v1/api_keys/dto.py
lockbox_sdk/v1/namespaces/__init__.py
lockbox_sdk/v1/namespaces/api.py
lockbox_sdk/v1/namespaces/client.py
lockbox_sdk/v1/namespaces/dto.py
lockbox_sdk/v1/tags/__init__.py
lockbox_sdk/v1/tags/api.py
lockbox_sdk/v1/tags/client.py
lockbox_sdk/v1/tags/dto.py
lockbox_sdk-0.1.2.dist-info/METADATA
lockbox_sdk-0.1.2.dist-info/WHEEL
lockbox_sdk-0.1.2.dist-info/licenses/LICENSE
lockbox_sdk-0.1.2.dist-info/RECORD
