Metadata-Version: 2.4
Name: lockbox-sdk
Version: 0.1.2
Summary: Python SDK for Lockbox API
Project-URL: repository, https://gitlab.com/wizrds/lockbox-sdk-py
Author-email: Tim Pogue <me@pogue.dev>
License: MIT
License-File: LICENSE
Classifier: Programming Language :: Python :: 3 :: Only
Classifier: Programming Language :: Python :: 3.9
Classifier: Programming Language :: Python :: 3.10
Classifier: Programming Language :: Python :: 3.11
Classifier: Programming Language :: Python :: 3.12
Classifier: Programming Language :: Python :: 3.13
Requires-Python: >=3.9
Requires-Dist: httpx>=0.28.1
Requires-Dist: pydantic>=2.11.7
